tantivy_mirror-0.17.0.dist-info/METADATA
tantivy_mirror-0.17.0.dist-info/WHEEL
tantivy_mirror-0.17.0.dist-info/license_files/LICENSE
tantivy/__init__.py
tantivy/tantivy.pypy37-pp73-x86_64-linux-gnu.so
tantivy_mirror-0.17.0.dist-info/RECORD
