Metadata-Version: 2.1
Name: tantivy-mirror
Version: 0.17.0
License-File: LICENSE
Author: Damir Jelić <poljar@termina.org.uk>
Author-email: Damir Jelić <poljar@termina.org.uk>
License: MIT
Requires-Python: >=3.7
